{"title":"测试下生成","date":"2019-03-19T08:46:30.000Z","slug":"page","comments":true,"tags":["test"],"updated":"2019-03-21T06:20:38.868Z","content":"","prev":{"title":"测试标签与分类","slug":"page_2"},"next":{"title":"Hello World","slug":"hello-world"},"link":"http://www.zqt0510.cn/post/page/","copyright":{"author":"Jessica","link":"<a href=\"http://www.zqt0510.cn/post/page/\" title=\"测试下生成\">http://www.zqt0510.cn/post/page/</a>","license":"自由转载-非商用-禁止演绎-保持署名 (<a href=\"https://creativecommons.org/licenses/by-nc-sa/4.0/\" rel=\"external nofollow noopener\" target=\"_blank\">CC BY-NC-ND 4.0</a>)"}}